{
  "id": "api-documents",
  "type": "api",
  "title": "Documents",
  "path": "/Users/aojdevstudio/cursor-projects/open-dental-scrape/docs/api-documentation/API Documents.txt",
  "content": "API Documents\nSee API Specification\n\nThis includes images, PDFs, etc. There are four ways a document can be inserted into Open Dental:\n\n1. Not using any API - Add a file to the patient folder. When the user later load the Imaging Module within Open Dental, any new files found are always recognized and entries are made in the database for them. By default, the new file will be dropped into the first category of images. If you want the new file to go to a specific category, then you can name it with a prefix of \"_##_\". Example: \"_135_\". The prefix number should be the DefNum of the category where the document belongs. To determine the DefNum, you will need to look in the database where definition.Category=18 and pick from that list somehow. Files with prefixes are processed to go into the specified category, and the prefix is removed.\n\n2. Documents POST SetByUrl.\n\n3. Documents POST Upload.\n\n4. Documents POST UploadSftp.\n\nDocuments GET (single)\nVersion Added: 24.2.32\n\nGets a single document. The result does not include the actual document file. Those can be obtained using Documents POST DownloadSftp.\n\nDocNum: Required in URL.\n\nExample Request:\nGET /documents/7\n\nExample Response:\n{\n\"DocNum\": 7,\n\"Description\": \"1-26-2009\",\n\"DateCreated\": \"2009-01-26 00:00:00\",\n\"DocCategory\": 190,\n\"docCategory\": \"Patient Pictures\",\n\"PatNum\": 15,\n\"FileName\": \"SmithJohn7.jpg\",\n\"ImgType\": \"Photo\",\n\"ToothNumbers\": \"\",\n\"DateTStamp\": \"2010-03-01 12:44:26\",\n\"ProvNum\": 0,\n\"PrintHeading\": \"false\"\n}\n\n200 OK\n404 NotFound (with explanation)\n\nDocuments GET (multiple)\nVersion Added: 21.2\n\nPatNum is required. Gets all documents and mounts for the patient, ordered by DateCreated. If the file storage method is InDatabase, the returned filePath field will be blank. Mounts do not have a filePath, ToothNumbers, PrintHeading, or a DateTStamp. The result does not include the actual document files. Those can be obtained using Documents POST DownloadSftp.\n\nExample Request:\nGET /documents?PatNum=101\n\nExample Response:\n[\n{\n\"DocNum\": 34,\n\"MountNum\": 0,\n\"filePath\": \"\\\\server\\\\OpenDentImages\\\\S\\\\SmithJohn15\\\\exampleimage.jpg\",\n\"Description\": \"Scanned image\",\n\"PatNum\": \"101\",\n\"Note\": \"\",\n\"DateCreated\": \"2021-04-08 08:12:21\",\n\"docCategory\": \"Lab Cases\",\n\"DocCategory\": 14,\n\"ToothNumbers\": \"1,2,3,4,5\",\n\"ProvNum\": \"0\",\n\"PrintHeading\": \"false\",\n\"DateTStamp\": \"2021-04-18 11:45:01\",\n\"serverDateTime\": \"2021-05-20 13:30:54\"\n},\n{\n\"DocNum\": 0,\n\"MountNum\": 15,\n\"filePath\": \"\",\n\"Description\": \" 5/11/2021: 4BW\",\n\"PatNum\": \"101\",\n\"Note\": \"Bitewings\",\n\"DateCreated\": \"2021-05-11 13:26:39\",\n\"docCategory\": \"Lab Cases\",\n\"DocCategory\": 14,\n\"ToothNumbers\": \"\",\n\"ProvNum\": \"0\",\n\"PrintHeading\": \"\",\n\"DateTStamp\": \"\",\n\"serverDateTime\": \"2021-05-20 13:30:54\"\n}\n]\n\n200 OK\n400 BadRequest \"PatNum is required\"\n404 NotFound \"Patient not found\"\n\nDocuments POST DownloadSftp\nVersion Added: 21.2\n\nThis will place a file on an SFTP site that you specify. After running this method, download the resulting file from your SFTP site. The user with the SFTP credentials must have write permission in this directory. Directory will be created if it does not exist, and files already existing with the specified name will be overwritten. If the SftpAddress does not contain a file name, the document.FileName will be used. All file storage options (LocalAtoZ, InDatabase, and Cloud) are supported.\n\nDocNum: This or MountNum is required.\nMountNum: This or DocNum is required.\nSftpAddress: Required. Specify the full path of the file (using /). The user with the SFTP credentials must have write permission in this directory.\nSftpUsername: Required.\nSftpPassword: Required.\n\nExample Requests:\nPOST /documents/DownloadSftp\n\n{\n\"DocNum\": 389,\n\"SftpAddress\": \"MySftpSite/myUsername/Documents/SmithJohn389.png\",\n\"SftpUsername\": \"myUsername\",\n\"SftpPassword\": \"myPassword\"\n}\n\n{\n\"MountNum\": 20,\n\"SftpAddress\": \"MySftpSite/myUsername/Documents/FMX.jpg\",\n\"SftpUsername\": \"myUsername\",\n\"SftpPassword\": \"myPassword\"\n}\n\nExample Response:\n201 Created, \"location\": The full filepath of the saved file.\n400 BadRequest (Invalid fields, invalid file extension, and Sftp connection errors)\n404 NotFound \"Document not found\" and \"Mount not found\".\n\nDocuments POST UploadSftp\nVersion Added: 21.2\n\nPrior to running this method, upload a file to your own SFTP site. This method will then pull the uploaded file into the customer's AtoZ folder, database, or cloud storage. The filePath of the response object will either be the full filepath of the saved file (AtoZ or cloud) or blank (database).\n\nPatNum: Required.\nSftpAddress: Required. Specify the full path of the file. The user with the SFTP credentials must have read permission in this directory.\nSftpUsername: Required.\nSftpPassword: Required.\n\nDescription: (Added in version 24.2.32) Optional. Default empty string.\nDateCreated: (Added in version 21.4) Optional. Defaults to today's date.\nDocCategory: Optional. Definition.DefNum where definition.Category=18. Defaults to the first definition in that category.\nImgType: Optional. Either Document, Radiograph, Photo, File or Attachment. Default is Document.\nToothNumbers: (Added in version 23.1.35) Optional. A string of numbers separated by commas and/or hyphen separated ranges.\nProvNum: (Added in version 24.2.32) Optional. Default 0.\nPrintHeading: (Added in version 24.2.32) Optional. Default \"false\".\n\nExample Request:\nPOST /documents/UploadSftp\n\n{\n\"PatNum\": 15,\n\"DateCreated\": \"2021-05-26 08:16:46\",\n\"DocCategory\": 14,\n\"ImgType\": \"Photo\",\n\"ToothNumbers\": \"1-5,8\",\n\"SftpAddress\": \"MySftpSite/myUsername/Documents/SmithJRadiograph.png\",\n\"SftpUsername\": \"myUsername\",\n\"SftpPassword\": \"myPassword\"\n}\n\nExample Response:\n{\n\"DocNum\": 411,\n\"filePath\": \"\\\\server\\OpenDentImages\\S\\SmithJohn15\\SmithJRadiograph.png\",\n\"Description\": \"SmithJRadiograph.png\",\n\"ToothNumbers\": \"1,2,3,4,5,8\",\n\"Note\": \"\",\n\"DateCreated\": \"2021-05-26 08:16:46\",\n\"DateTStamp\": \"2021-05-26 08:16:46\",\n\"DocCategory\": 14,\n\"docCategory\": \"Lab Cases\",\n\"serverDateTime\": \"2021-05-26 08:16:46\"\n}\n\n201 Created\n400 BadRequest (missing fields and Sftp connection errors)\n404 NotFound \"Patient not found\"\n\nDocuments POST Upload\nVersion Added: 21.1\n\nUpload the actual file as rawBase64. Specify the extension of the file. Examples could include .pdf, .jpg, .dcm, .doc, etc. rawBase64 goes into the database in document.Note as \"_rawBase64_:\" followed by the extension and rawBase64. Example: \"_rawBase64_:.jpg_errGEreRi3fWWtB+gWWEgg...\" The customer never sees this text, but when they later click on the document, the file is created and the note removed.\n\nPatNum: Required.\nrawBase64: Required.\nextension: Required.\n\nDescription: Optional.\nDateCreated: (Added in version 22.1) Optional. Default is today's date. String in \"yyyy-MM-dd HH:mm:ss\" format.\nDocCategory: Optional. FK to definition.ItemName, where definition.Category=18. Default is first in DocCategory.\nImgType: Optional. Either Document, Radiograph, Photo, File or Attachment. Default is Document.\nToothNumbers: (Added in version 23.1.35) Optional. A string of numbers separated by commas and/or hyphen separated ranges.\nProvNum: (Added in version 24.2.32) Optional. Default 0.\nPrintHeading: (Added in version 24.2.32) Optional. Default \"false\".\n\nExample Request:\nPOST /documents/Upload\n\n{\n\"PatNum\": 101,\n\"rawBase64\": \"errGEreRi3fWWtB+gWWEgg...\",\n\"extension\": \".jpg\",\n\"DocCategory\": 47,\n\"ImgType\": \"Photo\",\n\"Description\": \"Extraoral\",\n\"DateCreated\": \"2022-03-15 14:30:00\",\n\"ToothNumbers\": \"1-32\"\n}\n\nExample Response:\n{\n\"DocNum\": 93,\n\"Description\": \"Extraoral\",\n\"DateCreated\": \"2022-03-15 14:30:00\",\n\"DocCategory\": 47,\n\"docCategory\": \"Patient Pictures\",\n\"PatNum\": 101,\n\"FileName\": \"x\",\n\"ImgType\": \"Photo\",\n\"ToothNumbers\": \"1,2,3,4,5,6,7,8,9,10,11,12,13,14,15,16,17,18,19,20,21,22,23,24,25,26,27,28,29,30,31,32\",\n\"DateTStamp\": \"2024-09-24 11:18:57\",\n\"ProvNum\": 0,\n\"PrintHeading\": \"false\"\n}\n\n201 Created\n400 BadRequest (with explanation)\n404 NotFound (with explanation)\n\nDocuments POST Thumbnails\nVersion Added: 21.2\n\nPrior to running this method, first call a GET /documents for the patient to see their list of documents. Only standard image files from this list can be made into thumbnails. Mounts and pdfs will be skipped. This method gets the thumbnails for all images for the patient, creating any that do not already exist as thumbnails. Created thumbnails will be 100 x 100 and will use the same filename as the original image.\n\nThis will place files on an SFTP site that you specify. After running this method, download the resulting files from your SFTP site. The user with the SFTP credentials must have write permission in this directory. Directory will be created if it does not exist, and files already existing with the specified name will be overwritten. All file storage options (LocalAtoZ, InDatabase, and Cloud) are supported.\n\nPatNum: Required.\nSftpAddress: Required. Specify the full path of the file. The user with the SFTP credentials must have read permission in this directory.\nSftpUsername: Required.\nSftpPassword: Required.\n\nExample Request:\nPOST /documents/Thumbnails\n\n{\n\"PatNum\": 15,\n\"SftpAddress\": \"MySftpSite/myUsername/Thumbnails/\",\n\"SftpUsername\": \"myUsername\",\n\"SftpPassword\": \"myPassword\"\n}\n\nExample Responses:\n[\n{\n\"DocNum\": 440,\n\"FileName\": \"SmithJohn440.gif\"\n},\n{\n\"DocNum\": 441,\n\"FileName\": \"SmithJohn441.gif\"\n}\n]\n\n200 OK \"No documents could be made into thumbnails.\"\n201 Created\n400 BadRequest (missing fields and Sftp connection errors)\n404 NotFound \"Patient not found\" and \"No documents exist for this patient\"\n\nDocuments POST DownloadMount\nVersion Added: 21.2\n\nYou probably don't want to use this. Gets all the individual images for one mount, but there's no information about which position in the mount, flipping, rotation, etc. It is much more common to use Documents POST DownloadSftp to get a composite image for a mount instead of the individual images.\n\nPrior to running this method, first call a GET /documents for the patient to see their list of documents and mounts. Use the MountNum to run this method. All images in the mount will be downloaded to the specified folder. Created files will use the same filename as the original image.\n\nThis will place files on an SFTP site that you specify. After running this method, download the resulting files from your SFTP site. The user with the SFTP credentials must have write permission in this directory. Directory will be created if it does not exist, and files already existing with the same name will be overwritten. All file storage options (LocalAtoZ, InDatabase, and Cloud) are supported.\n\nMountNum: Required.\nSftpAddress: Required. Specify the full path of the file. The user with the SFTP credentials must have read permission in this directory.\nSftpUsername: Required.\nSftpPassword: Required.\n\nExample Request:\nPOST /documents/DownloadMount\n\n{\n\"MountNum\": 15,\n\"SftpAddress\": \"MySftpSite/myUsername/Mounts/\",\n\"SftpUsername\": \"myUsername\",\n\"SftpPassword\": \"myPassword\"\n}\n\nExample Responses:\n[\n{\n\"DocNum\": 440,\n\"FileName\": \"SmithJohn440.gif\"\n},\n{\n\"DocNum\": 441,\n\"FileName\": \"SmithJohn441.gif\"\n}\n]\n\n200 OK \"No mount images could be downloaded.\"\n201 Created\n400 BadRequest (missing fields and Sftp connection errors)\n404 NotFound \"Mount not found.\"\n\nDocuments POST SetByUrl\nVersion Added: 21.1\n\nURL goes into the database in document.Note as \"_download_:\" followed by the URL. The customer never sees this text, but when they later click on the document, the URL is used to perform a download and the prefix is removed.\n\nPatNum: Required.\nurl: Required.\n\nDescription: Optional.\nDateCreated: (Added in version 24.2.32) Optional. Default is today's date. String in \"yyyy-MM-dd HH:mm:ss\" format.\nDocCategory: Optional. FK to definition.ItemName, where definition.Category=18. Default is first in DocCategory.\nImgType: Optional. Either Document, Radiograph, Photo, File or Attachment. Default is Document.\nToothNumbers: (Added in version 23.1.35) Optional. A string of numbers separated by commas and/or hyphen separated ranges.\nProvNum: (Added in version 24.2.32) Optional. Default 0.\nPrintHeading: (Added in version 24.2.32) Optional. Default \"false\".\n\nExample Request:\nPOST /documents/SetByUrl\n\n{\n\"PatNum\": 101,\n\"url\": \"https://www.somesite.com/myimage.jpg\",\n\"DocCategory\": 47,\n\"Description\": \"Extraoral\",\n\"ImgType\": \"Photo\",\n\"ToothNumbers\": \"1,2\"\n}\n\nExample Response:\n{\n\"DocNum\": 94,\n\"Description\": \"Extraoral\",\n\"DateCreated\": \"2024-09-24 11:45:52\",\n\"DocCategory\": 47,\n\"docCategory\": \"Patient Pictures\",\n\"PatNum\": 101,\n\"FileName\": \"xx\",\n\"ImgType\": \"Photo\",\n\"ToothNumbers\": \"1,2\",\n\"DateTStamp\": \"2024-09-24 11:45:52\",\n\"ProvNum\": 0,\n\"PrintHeading\": \"false\"\n}\n\n201 Created\n400 BadRequest (with explanation)\n404 NotFound (with explanation)\n\nDocuments PUT (update)\nVersion Added: 24.2.32\n\nUpdates Image Info of an existing document.\n\nDocNum: Required in URL.\n\nDescription: Description that will show on the image category tree.\nDateCreated: String in \"yyyy-MM-dd HH:mm:ss\" format.\nDocCategory: definition.DefNum where definition.Category=18.\nImgType: Either \"Document\", \"Radiograph\", \"Photo\", \"File\", or \"Attachment\".\nToothNumbers: A string of numbers separated by commas and/or hyphen separated ranges.\nProvNum: ProvNum of a non-hidden provider.\nPrintHeading: Either \"true\" or \"false\". If true, additional information will be displayed when this document is printed.\n\nExample Request:\nPUT /documents/27\n\n{\n\"Description\": \"Pano\",\n\"DateCreated\": \"2024-01-25 07:45:35\",\n\"DocCategory\": 190,\n\"ImgType\": \"Radiograph\",\n\"ToothNumbers\": \"12-15,20,21\",\n\"ProvNum\": 2,\n\"PrintHeading\": \"true\"\n}\n\nExample Response:\n{\n\"DocNum\": 27,\n\"Description\": \"Pano\",\n\"DateCreated\": \"2024-01-25 07:45:35\",\n\"DocCategory\": 190,\n\"docCategory\": \"Xray\",\n\"PatNum\": 11,\n\"FileName\": \"AllowedAllenRadio.jpg\",\n\"ImgType\": \"Radiograph\",\n\"ToothNumbers\": \"12,13,14,15,20,21\",\n\"DateTStamp\": \"2024-08-20 15:58:13\",\n\"ProvNum\": 2,\n\"PrintHeading\": \"true\"\n}\n\n200 OK\n400 BadRequest (with explanation)\n404 NotFound (with explanation)\n\nDocuments DELETE\nVersion Added: 24.2.32\n\nDeletes a document. Deletes both the database row and any associated file from the A to Z folder.\n\nDocNum: Required in the URL.\n\nExample Request:\nDELETE /documents/27\n\nExample Responses:\n200 OK\n400 BadRequest (with explanation)\n404 NotFound (with explanation)",
  "metadata": {
    "version": "24.2.32",
    "lastUpdated": "",
    "category": [
      "API"
    ],
    "tags": [
      "Documents",
      "GET",
      "POST",
      "PUT",
      "DELETE",
      "Required Fields",
      "Examples"
    ]
  },
  "endpoints": [
    {
      "resource": "Documents",
      "method": "POST",
      "path": "/documents",
      "versionAdded": "21.2",
      "parameters": [],
      "examples": [
        {
          "request": "POST /documents/DownloadSftp\n\n{\n\"DocNum\": 389,\n\"SftpAddress\": \"MySftpSite/myUsername/Documents/SmithJohn389.png\",\n\"SftpUsername\": \"myUsername\",\n\"SftpPassword\": \"myPassword\"\n}\n\n{\n\"MountNum\": 20,\n\"SftpAddress\": \"MySftpSite/myUsername/Documents/FMX.jpg\",\n\"SftpUsername\": \"myUsername\",\n\"SftpPassword\": \"myPassword\"\n}",
          "response": ""
        }
      ],
      "responses": [
        {
          "code": "201",
          "status": "Created",
          "description": ""
        },
        {
          "code": "400",
          "status": "BadRequest",
          "description": "Invalid fields, invalid file extension, and Sftp connection errors"
        },
        {
          "code": "404",
          "status": "NotFound",
          "description": ""
        }
      ],
      "description": "This will place a file on an SFTP site that you specify. After running this method, download the resulting file from your SFTP site. The user with the SFTP credentials must have write permission in this directory. Directory will be created if it does not exist, and files already existing with the specified name will be overwritten. If the SftpAddress does not contain a file name, the document.FileName will be used. All file storage options (LocalAtoZ, InDatabase, and Cloud) are supported."
    },
    {
      "resource": "Documents",
      "method": "POST",
      "path": "/documents",
      "versionAdded": "21.2",
      "parameters": [],
      "examples": [
        {
          "request": "POST /documents/UploadSftp\n\n{\n\"PatNum\": 15,\n\"DateCreated\": \"2021-05-26 08:16:46\",\n\"DocCategory\": 14,\n\"ImgType\": \"Photo\",\n\"ToothNumbers\": \"1-5,8\",\n\"SftpAddress\": \"MySftpSite/myUsername/Documents/SmithJRadiograph.png\",\n\"SftpUsername\": \"myUsername\",\n\"SftpPassword\": \"myPassword\"\n}",
          "response": "{\n\"DocNum\": 411,\n\"filePath\": \"\\\\server\\OpenDentImages\\S\\SmithJohn15\\SmithJRadiograph.png\",\n\"Description\": \"SmithJRadiograph.png\",\n\"ToothNumbers\": \"1,2,3,4,5,8\",\n\"Note\": \"\",\n\"DateCreated\": \"2021-05-26 08:16:46\",\n\"DateTStamp\": \"2021-05-26 08:16:46\",\n\"DocCategory\": 14,\n\"docCategory\": \"Lab Cases\",\n\"serverDateTime\": \"2021-05-26 08:16:46\"\n}"
        }
      ],
      "responses": [
        {
          "code": "201",
          "status": "Created",
          "description": ""
        },
        {
          "code": "400",
          "status": "BadRequest",
          "description": "missing fields and Sftp connection errors"
        },
        {
          "code": "404",
          "status": "NotFound",
          "description": ""
        }
      ],
      "description": "Prior to running this method, upload a file to your own SFTP site. This method will then pull the uploaded file into the customer's AtoZ folder, database, or cloud storage. The filePath of the response object will either be the full filepath of the saved file (AtoZ or cloud) or blank (database)."
    },
    {
      "resource": "Documents",
      "method": "POST",
      "path": "/documents",
      "versionAdded": "21.1",
      "parameters": [],
      "examples": [
        {
          "request": "POST /documents/Upload\n\n{\n\"PatNum\": 101,\n\"rawBase64\": \"errGEreRi3fWWtB+gWWEgg...\",\n\"extension\": \".jpg\",\n\"DocCategory\": 47,\n\"ImgType\": \"Photo\",\n\"Description\": \"Extraoral\",\n\"DateCreated\": \"2022-03-15 14:30:00\",\n\"ToothNumbers\": \"1-32\"\n}",
          "response": "{\n\"DocNum\": 93,\n\"Description\": \"Extraoral\",\n\"DateCreated\": \"2022-03-15 14:30:00\",\n\"DocCategory\": 47,\n\"docCategory\": \"Patient Pictures\",\n\"PatNum\": 101,\n\"FileName\": \"x\",\n\"ImgType\": \"Photo\",\n\"ToothNumbers\": \"1,2,3,4,5,6,7,8,9,10,11,12,13,14,15,16,17,18,19,20,21,22,23,24,25,26,27,28,29,30,31,32\",\n\"DateTStamp\": \"2024-09-24 11:18:57\",\n\"ProvNum\": 0,\n\"PrintHeading\": \"false\"\n}"
        }
      ],
      "responses": [
        {
          "code": "201",
          "status": "Created",
          "description": ""
        },
        {
          "code": "400",
          "status": "BadRequest",
          "description": "with explanation"
        },
        {
          "code": "404",
          "status": "NotFound",
          "description": "with explanation"
        }
      ],
      "description": "Upload the actual file as rawBase64. Specify the extension of the file."
    },
    {
      "resource": "Documents",
      "method": "POST",
      "path": "/documents",
      "versionAdded": "21.2",
      "parameters": [],
      "examples": [
        {
          "request": "POST /documents/Thumbnails\n\n{\n\"PatNum\": 15,\n\"SftpAddress\": \"MySftpSite/myUsername/Thumbnails/\",\n\"SftpUsername\": \"myUsername\",\n\"SftpPassword\": \"myPassword\"\n}",
          "response": ""
        }
      ],
      "responses": [
        {
          "code": "100",
          "status": "x",
          "description": ""
        },
        {
          "code": "100",
          "status": "and",
          "description": ""
        },
        {
          "code": "200",
          "status": "OK",
          "description": ""
        },
        {
          "code": "201",
          "status": "Created",
          "description": ""
        },
        {
          "code": "400",
          "status": "BadRequest",
          "description": "missing fields and Sftp connection errors"
        },
        {
          "code": "404",
          "status": "NotFound",
          "description": ""
        }
      ],
      "description": "Prior to running this method, first call a GET /documents for the patient to see their list of documents. Only standard image files from this list can be made into thumbnails. Mounts and pdfs will be skipped. This method gets the thumbnails for all images for the patient, creating any that do not already exist as thumbnails. Created thumbnails will be   will use the same filename as the original image."
    },
    {
      "resource": "Documents",
      "method": "POST",
      "path": "/documents",
      "versionAdded": "21.2",
      "parameters": [],
      "examples": [
        {
          "request": "POST /documents/DownloadMount\n\n{\n\"MountNum\": 15,\n\"SftpAddress\": \"MySftpSite/myUsername/Mounts/\",\n\"SftpUsername\": \"myUsername\",\n\"SftpPassword\": \"myPassword\"\n}",
          "response": ""
        }
      ],
      "responses": [
        {
          "code": "200",
          "status": "OK",
          "description": ""
        },
        {
          "code": "201",
          "status": "Created",
          "description": ""
        },
        {
          "code": "400",
          "status": "BadRequest",
          "description": "missing fields and Sftp connection errors"
        },
        {
          "code": "404",
          "status": "NotFound",
          "description": ""
        }
      ],
      "description": "You probably don't want to use this. Gets all the individual images for one mount, but there's no information about which position in the mount, flipping, rotation, etc. It is much more common to use Documents POST DownloadSftp to get a composite image for a mount instead of the individual images."
    },
    {
      "resource": "Documents",
      "method": "POST",
      "path": "/documents",
      "versionAdded": "21.1",
      "parameters": [],
      "examples": [
        {
          "request": "POST /documents/SetByUrl\n\n{\n\"PatNum\": 101,\n\"url\": \"https://www.somesite.com/myimage.jpg\",\n\"DocCategory\": 47,\n\"Description\": \"Extraoral\",\n\"ImgType\": \"Photo\",\n\"ToothNumbers\": \"1,2\"\n}",
          "response": "{\n\"DocNum\": 94,\n\"Description\": \"Extraoral\",\n\"DateCreated\": \"2024-09-24 11:45:52\",\n\"DocCategory\": 47,\n\"docCategory\": \"Patient Pictures\",\n\"PatNum\": 101,\n\"FileName\": \"xx\",\n\"ImgType\": \"Photo\",\n\"ToothNumbers\": \"1,2\",\n\"DateTStamp\": \"2024-09-24 11:45:52\",\n\"ProvNum\": 0,\n\"PrintHeading\": \"false\"\n}"
        }
      ],
      "responses": [
        {
          "code": "201",
          "status": "Created",
          "description": ""
        },
        {
          "code": "400",
          "status": "BadRequest",
          "description": "with explanation"
        },
        {
          "code": "404",
          "status": "NotFound",
          "description": "with explanation"
        }
      ],
      "description": "URL goes into the database in document.Note as \"_download_:\" followed by the URL. The customer never sees this text, but when they later click on the document, the URL is used to perform a download and the prefix is removed."
    },
    {
      "resource": "Documents",
      "method": "DELETE",
      "path": "/documents",
      "versionAdded": "24.2.32",
      "parameters": [],
      "examples": [
        {
          "request": "DELETE /documents/27",
          "response": ""
        }
      ],
      "responses": [
        {
          "code": "200",
          "status": "OK",
          "description": ""
        },
        {
          "code": "400",
          "status": "BadRequest",
          "description": "with explanation"
        },
        {
          "code": "404",
          "status": "NotFound",
          "description": "with explanation"
        }
      ],
      "description": "Deletes a document. Deletes both the database row and any associated file from the A to Z folder."
    }
  ],
  "relationships": [
    {
      "type": "references",
      "target": "db-patient",
      "description": "API references database table patient"
    },
    {
      "type": "references",
      "target": "db-document",
      "description": "API references database table document"
    },
    {
      "type": "references",
      "target": "db-site",
      "description": "API references database table site"
    },
    {
      "type": "references",
      "target": "db-mount",
      "description": "API references database table mount"
    },
    {
      "type": "references",
      "target": "db-definition",
      "description": "API references database table definition"
    },
    {
      "type": "references",
      "target": "db-provider",
      "description": "API references database table provider"
    }
  ]
}