{
  "id": "api-discountplansubs",
  "type": "api",
  "title": "DiscountPlanSubs",
  "path": "/Users/aojdevstudio/cursor-projects/open-dental-scrape/docs/api-documentation/API DiscountPlanSubs.txt",
  "content": "API DiscountPlanSubs\nSee API Specification\n\nSee Discount Plan for more information.\n\nDiscountPlanSubs GET\nVersion Added: 21.3\n\nGets a DiscountPlanSub from a patient that is subscribed to a Discount Plan.\n\nPatNum: Required.\n\nExample Request:\nGET /discountplansubs?PatNum=56\n\nExample Response:\n{\n\"DiscountSubNum\": 32,\n\"DiscountPlanNum\": 8,\n\"PatNum\": 56,\n\"DateEffective\": \"2021-01-01\",\n\"DateTerm\": \"2022-01-01\",\n\"SubNote\": \"\"\n}\n\n200 OK\n400 BadRequest (with explanation)\n404 NotFound (with explanation)\n\nDiscountPlanSubs POST\nVersion Added: 21.3\n\nSubscribes a patient to an existing DiscountPlan.\n\nDiscountPlanNum: Required.\nPatNum: Required.\n\nDateEffective: Optional. String in \"yyyy-MM-dd\" format. The date when the plan will start impacting procedure fees. Default \"0001-01-01\" to indicate the beginning of the current calendar year.\nDateTerm: Optional. String in \"yyyy-MM-dd\" format. The date when the plan will no longer impact procedure fees. Default \"0001-01-01\" to indicate no end date.\nSubNote: Optional. Subscriber note.\n\nExample Request:\nPOST /discountplansubs\n\n{\n\"DiscountPlanNum\": 6,\n\"PatNum\": 67,\n\"DateEffective\": \"2021-01-01\",\n\"DateTerm\": \"2022-01-01\"\n}\n\nExample Response:\n201 Created\n400 BadRequest (with explanation)\n404 NotFound (with explanation)\n\nDiscountPlanSubs PUT\nVersion Added: 22.3.13\n\nUpdates an existing DiscountPlanSub. Updating SubNote will overwrite the existing subscriber note.\n\nDiscountSubNum: Required in the URL.\nPatNum: Required. The PatNum attached to the DiscountPlanSub.\n\nDateEffective: Optional. String in \"yyyy-MM-dd\" format.\nDateTerm: Optional. String in \"yyyy-MM-dd\" format.\nSubNote: Optional. Subscriber note.\n\nExample Request:\nPUT /discountplansubs/14\n\n{\n\"PatNum\": 23,\n\"DateEffective\": \"2022-09-16\",\n\"DateTerm\": \"2024-12-31\",\n\"SubNote\": \"25% discount to services.\"\n}\n\nExample Response:\n200 OK\n400 BadRequest (with explanation)\n404 NotFound (with explanation)\n\nDiscountPlanSubs DELETE\nVersion Added: 23.1.12\n\nDeletes an existing DiscountPlanSub.\n\nDiscountSubNum: Required in URL.\n\nExample Request:\nDELETE /discountplansubs/14\n\nExample Response:\n200 OK\n400 BadRequest (with explanation)\n404 NotFound (with explanation)",
  "metadata": {
    "version": "23.1.12",
    "lastUpdated": "",
    "category": [
      "API"
    ],
    "tags": [
      "DiscountPlanSubs",
      "GET",
      "POST",
      "PUT",
      "DELETE",
      "Required Fields",
      "Examples"
    ]
  },
  "endpoints": [
    {
      "resource": "DiscountPlanSubs",
      "method": "GET",
      "path": "/discountplansubs",
      "versionAdded": "21.3",
      "parameters": [],
      "examples": [
        {
          "request": "GET /discountplansubs?PatNum=56",
          "response": "{\n\"DiscountSubNum\": 32,\n\"DiscountPlanNum\": 8,\n\"PatNum\": 56,\n\"DateEffective\": \"2021-01-01\",\n\"DateTerm\": \"2022-01-01\",\n\"SubNote\": \"\"\n}"
        }
      ],
      "responses": [
        {
          "code": "200",
          "status": "OK",
          "description": ""
        },
        {
          "code": "400",
          "status": "BadRequest",
          "description": "with explanation"
        },
        {
          "code": "404",
          "status": "NotFound",
          "description": "with explanation"
        }
      ],
      "description": "Gets a DiscountPlanSub from a patient that is subscribed to a Discount Plan."
    },
    {
      "resource": "DiscountPlanSubs",
      "method": "POST",
      "path": "/discountplansubs",
      "versionAdded": "21.3",
      "parameters": [],
      "examples": [
        {
          "request": "POST /discountplansubs\n\n{\n\"DiscountPlanNum\": 6,\n\"PatNum\": 67,\n\"DateEffective\": \"2021-01-01\",\n\"DateTerm\": \"2022-01-01\"\n}",
          "response": ""
        }
      ],
      "responses": [
        {
          "code": "201",
          "status": "Created",
          "description": ""
        },
        {
          "code": "400",
          "status": "BadRequest",
          "description": "with explanation"
        },
        {
          "code": "404",
          "status": "NotFound",
          "description": "with explanation"
        }
      ],
      "description": "Subscribes a patient to an existing DiscountPlan."
    },
    {
      "resource": "DiscountPlanSubs",
      "method": "PUT",
      "path": "/discountplansubs",
      "versionAdded": "22.3.13",
      "parameters": [],
      "examples": [
        {
          "request": "PUT /discountplansubs/14\n\n{\n\"PatNum\": 23,\n\"DateEffective\": \"2022-09-16\",\n\"DateTerm\": \"2024-12-31\",\n\"SubNote\": \"25% discount to services.\"\n}",
          "response": ""
        }
      ],
      "responses": [
        {
          "code": "200",
          "status": "OK",
          "description": ""
        },
        {
          "code": "400",
          "status": "BadRequest",
          "description": "with explanation"
        },
        {
          "code": "404",
          "status": "NotFound",
          "description": "with explanation"
        }
      ],
      "description": "Updates an existing DiscountPlanSub. Updating SubNote will overwrite the existing subscriber note."
    },
    {
      "resource": "DiscountPlanSubs",
      "method": "DELETE",
      "path": "/discountplansubs",
      "versionAdded": "23.1.12",
      "parameters": [],
      "examples": [
        {
          "request": "DELETE /discountplansubs/14",
          "response": ""
        }
      ],
      "responses": [
        {
          "code": "200",
          "status": "OK",
          "description": ""
        },
        {
          "code": "400",
          "status": "BadRequest",
          "description": "with explanation"
        },
        {
          "code": "404",
          "status": "NotFound",
          "description": "with explanation"
        }
      ],
      "description": "Deletes an existing DiscountPlanSub."
    }
  ],
  "relationships": [
    {
      "type": "references",
      "target": "db-patient",
      "description": "API references database table patient"
    },
    {
      "type": "references",
      "target": "db-document",
      "description": "API references database table document"
    },
    {
      "type": "references",
      "target": "db-discountplansub",
      "description": "API references database table discountplansub"
    },
    {
      "type": "references",
      "target": "db-fee",
      "description": "API references database table fee"
    },
    {
      "type": "references",
      "target": "db-discountplan",
      "description": "API references database table discountplan"
    }
  ]
}